{
    "sources": {
        "GIBS:epsg3413:all": {
            "url": [
                "//cache1-sit.gibs.earthdata.nasa.gov/wmts/epsg3413/all/wmts.cgi"
            ]
        },
        "GIBS:epsg3413:best": {
            "url": [
                "//cache1-sit.gibs.earthdata.nasa.gov/wmts/epsg3413/best/wmts.cgi"
            ]
        },
        "GIBS:epsg3413:nrt": {
            "url": [
                "//cache1-sit.gibs.earthdata.nasa.gov/wmts/epsg3413/nrt/wmts.cgi"
            ]
        },
        "GIBS:epsg3413:std": {
            "url": [
                "//cache1-sit.gibs.earthdata.nasa.gov/wmts/epsg3413/std/wmts.cgi"
            ]
        },
        "GIBS:epsg3031:all": {
            "url": [
                "//cache1-sit.gibs.earthdata.nasa.gov/wmts/epsg3031/all/wmts.cgi"
            ]
        },
        "GIBS:epsg3031:best": {
            "url": [
                "//cache1-sit.gibs.earthdata.nasa.gov/wmts/epsg3031/best/wmts.cgi"
            ]
        },
        "GIBS:epsg3031:nrt": {
            "url": [
                "//cache1-sit.gibs.earthdata.nasa.gov/wmts/epsg3031/nrt/wmts.cgi"
            ]
        },
        "GIBS:epsg3031:std": {
            "url": [
                "//cache1-sit.gibs.earthdata.nasa.gov/wmts/epsg3031/std/wmts.cgi"
            ]
        },
        "GIBS:epsg4326:all": {
            "url": [
                "//cache1-sit.gibs.earthdata.nasa.gov/wmts/epsg4326/all/wmts.cgi"
            ]
        },
        "GIBS:epsg4326:best": {
            "url": [
                "//cache1-sit.gibs.earthdata.nasa.gov/wmts/epsg4326/best/wmts.cgi"
            ]
        },
        "GIBS:epsg4326:nrt": {
            "url": [
                "//cache1-sit.gibs.earthdata.nasa.gov/wmts/epsg4326/nrt/wmts.cgi"
            ]
        },
        "GIBS:epsg4326:std": {
            "url": [
                "//cache1-sit.gibs.earthdata.nasa.gov/wmts/epsg4326/std/wmts.cgi"
            ]
        },
        "GIBS:epsg3857:all": {
            "url": [
                "//cache1-sit.gibs.earthdata.nasa.gov/wmts/epsg3857/all/wmts.cgi"
            ]
        },
        "GIBS:epsg3857:best": {
            "url": [
                "//cache1-sit.gibs.earthdata.nasa.gov/wmts/epsg3857/best/wmts.cgi"
            ]
        },
        "GIBS:epsg3857:nrt": {
            "url": [
                "//cache1-sit.gibs.earthdata.nasa.gov/wmts/epsg3857/nrt/wmts.cgi"
            ]
        },
        "GIBS:epsg3857:std": {
            "url": [
                "//cache1-sit.gibs.earthdata.nasa.gov/wmts/epsg3857/std/wmts.cgi"
            ]
        },
        "GIBS:wms": {
            "url": [
                "//cache1-sit.gibs.earthdata.nasa.gov/wms/wms.php"
            ]
        }
    }
}
